{
  "generated_at": "2026-07-17T17:32:49.970Z",
  "date": "2026-07-17",
  "match_count": 51,
  "policy": "Lineup and player ability data is filled by trusted manual import or approved source adapters.",
  "matches": [
    {
      "match_name": "Rennes VS Guingamp",
      "league": "Hazırlık Kulüpler",
      "start_time": "18:30",
      "home_lineup": {
        "team_name": "Rennes",
        "formation": "-",
        "starting_11_count": 0,
        "substitutes_count": 0,
        "starting_11_strength": 0,
        "bench_strength": 0,
        "strength_label": "Veri Yok",
        "top_starting_players": [],
        "top_bench_players": [],
        "unavailable_players": [],
        "important_missing_count": 0,
        "note": "",
        "source_note": ""
      },
      "away_lineup": {
        "team_name": "Guingamp",
        "formation": "-",
        "starting_11_count": 0,
        "substitutes_count": 0,
        "starting_11_strength": 0,
        "bench_strength": 0,
        "strength_label": "Veri Yok",
        "top_starting_players": [],
        "top_bench_players": [],
        "unavailable_players": [],
        "important_missing_count": 0,
        "note": "",
        "source_note": ""
      },
      "lineup_quality_diff": 0,
      "lineup_risk_level": "Düşük",
      "robot_comment": "İlk 11 kalite verisi yok. Kadro eksikliği riski: Düşük."
    },
    {
      "match_name": "Voluntari VS Botosani",
      "league": "Romanya 1.Lig",
      "start_time": "18:30",
      "home_lineup": {
        "team_name": "Voluntari",
        "formation": "-",
        "starting_11_count": 0,
        "substitutes_count": 0,
        "starting_11_strength": 0,
        "bench_strength": 0,
        "strength_label": "Veri Yok",
        "top_starting_players": [],
        "top_bench_players": [],
        "unavailable_players": [],
        "important_missing_count": 0,
        "note": "",
        "source_note": ""
      },
      "away_lineup": {
        "team_name": "Botosani",
        "formation": "-",
        "starting_11_count": 0,
        "substitutes_count": 0,
        "starting_11_strength": 0,
        "bench_strength": 0,
        "strength_label": "Veri Yok",
        "top_starting_players": [],
        "top_bench_players": [],
        "unavailable_players": [],
        "important_missing_count": 0,
        "note": "",
        "source_note": ""
      },
      "lineup_quality_diff": 0,
      "lineup_risk_level": "Düşük",
      "robot_comment": "İlk 11 kalite verisi yok. Kadro eksikliği riski: Düşük."
    },
    {
      "match_name": "Lokomotiva VS Karpaty Lviv",
      "league": "Hazırlık Kulüpler",
      "start_time": "18:30",
      "home_lineup": {
        "team_name": "Lokomotiva",
        "formation": "-",
        "starting_11_count": 0,
        "substitutes_count": 0,
        "starting_11_strength": 0,
        "bench_strength": 0,
        "strength_label": "Veri Yok",
        "top_starting_players": [],
        "top_bench_players": [],
        "unavailable_players": [],
        "important_missing_count": 0,
        "note": "",
        "source_note": ""
      },
      "away_lineup": {
        "team_name": "Karpaty Lviv",
        "formation": "-",
        "starting_11_count": 0,
        "substitutes_count": 0,
        "starting_11_strength": 0,
        "bench_strength": 0,
        "strength_label": "Veri Yok",
        "top_starting_players": [],
        "top_bench_players": [],
        "unavailable_players": [],
        "important_missing_count": 0,
        "note": "",
        "source_note": ""
      },
      "lineup_quality_diff": 0,
      "lineup_risk_level": "Düşük",
      "robot_comment": "İlk 11 kalite verisi yok. Kadro eksikliği riski: Düşük."
    },
    {
      "match_name": "Bayreuth VS Carl Zeiss Jena",
      "league": "Hazırlık Kulüpler",
      "start_time": "19:00",
      "home_lineup": {
        "team_name": "Bayreuth",
        "formation": "-",
        "starting_11_count": 0,
        "substitutes_count": 0,
        "starting_11_strength": 0,
        "bench_strength": 0,
        "strength_label": "Veri Yok",
        "top_starting_players": [],
        "top_bench_players": [],
        "unavailable_players": [],
        "important_missing_count": 0,
        "note": "",
        "source_note": ""
      },
      "away_lineup": {
        "team_name": "Carl Zeiss Jena",
        "formation": "-",
        "starting_11_count": 0,
        "substitutes_count": 0,
        "starting_11_strength": 0,
        "bench_strength": 0,
        "strength_label": "Veri Yok",
        "top_starting_players": [],
        "top_bench_players": [],
        "unavailable_players": [],
        "important_missing_count": 0,
        "note": "",
        "source_note": ""
      },
      "lineup_quality_diff": 0,
      "lineup_risk_level": "Düşük",
      "robot_comment": "İlk 11 kalite verisi yok. Kadro eksikliği riski: Düşük."
    },
    {
      "match_name": "Paderborn VS Fagiano Okayama",
      "league": "Hazırlık Kulüpler",
      "start_time": "19:00",
      "home_lineup": {
        "team_name": "Paderborn",
        "formation": "-",
        "starting_11_count": 0,
        "substitutes_count": 0,
        "starting_11_strength": 0,
        "bench_strength": 0,
        "strength_label": "Veri Yok",
        "top_starting_players": [],
        "top_bench_players": [],
        "unavailable_players": [],
        "important_missing_count": 0,
        "note": "",
        "source_note": ""
      },
      "away_lineup": {
        "team_name": "Fagiano Okayama",
        "formation": "-",
        "starting_11_count": 0,
        "substitutes_count": 0,
        "starting_11_strength": 0,
        "bench_strength": 0,
        "strength_label": "Veri Yok",
        "top_starting_players": [],
        "top_bench_players": [],
        "unavailable_players": [],
        "important_missing_count": 0,
        "note": "",
        "source_note": ""
      },
      "lineup_quality_diff": 0,
      "lineup_risk_level": "Düşük",
      "robot_comment": "İlk 11 kalite verisi yok. Kadro eksikliği riski: Düşük."
    },
    {
      "match_name": "Spartak Varna VS Cska 1948 Sofia",
      "league": "Bulgaristan 1.Lig",
      "start_time": "19:00",
      "home_lineup": {
        "team_name": "Spartak Varna",
        "formation": "-",
        "starting_11_count": 0,
        "substitutes_count": 0,
        "starting_11_strength": 0,
        "bench_strength": 0,
        "strength_label": "Veri Yok",
        "top_starting_players": [],
        "top_bench_players": [],
        "unavailable_players": [],
        "important_missing_count": 0,
        "note": "",
        "source_note": ""
      },
      "away_lineup": {
        "team_name": "Cska 1948 Sofia",
        "formation": "-",
        "starting_11_count": 0,
        "substitutes_count": 0,
        "starting_11_strength": 0,
        "bench_strength": 0,
        "strength_label": "Veri Yok",
        "top_starting_players": [],
        "top_bench_players": [],
        "unavailable_players": [],
        "important_missing_count": 0,
        "note": "",
        "source_note": ""
      },
      "lineup_quality_diff": 0,
      "lineup_risk_level": "Düşük",
      "robot_comment": "İlk 11 kalite verisi yok. Kadro eksikliği riski: Düşük."
    },
    {
      "match_name": "Kapa VS Sjk Ii",
      "league": "Finlandiya Ykkösliiga",
      "start_time": "19:00",
      "home_lineup": {
        "team_name": "Kapa",
        "formation": "-",
        "starting_11_count": 0,
        "substitutes_count": 0,
        "starting_11_strength": 0,
        "bench_strength": 0,
        "strength_label": "Veri Yok",
        "top_starting_players": [],
        "top_bench_players": [],
        "unavailable_players": [],
        "important_missing_count": 0,
        "note": "",
        "source_note": ""
      },
      "away_lineup": {
        "team_name": "Sjk Ii",
        "formation": "-",
        "starting_11_count": 0,
        "substitutes_count": 0,
        "starting_11_strength": 0,
        "bench_strength": 0,
        "strength_label": "Veri Yok",
        "top_starting_players": [],
        "top_bench_players": [],
        "unavailable_players": [],
        "important_missing_count": 0,
        "note": "",
        "source_note": ""
      },
      "lineup_quality_diff": 0,
      "lineup_risk_level": "Düşük",
      "robot_comment": "İlk 11 kalite verisi yok. Kadro eksikliği riski: Düşük."
    },
    {
      "match_name": "Klubi 04 VS Haka",
      "league": "Finlandiya Ykkösliiga",
      "start_time": "19:00",
      "home_lineup": {
        "team_name": "Klubi 04",
        "formation": "-",
        "starting_11_count": 0,
        "substitutes_count": 0,
        "starting_11_strength": 0,
        "bench_strength": 0,
        "strength_label": "Veri Yok",
        "top_starting_players": [],
        "top_bench_players": [],
        "unavailable_players": [],
        "important_missing_count": 0,
        "note": "",
        "source_note": ""
      },
      "away_lineup": {
        "team_name": "Haka",
        "formation": "-",
        "starting_11_count": 0,
        "substitutes_count": 0,
        "starting_11_strength": 0,
        "bench_strength": 0,
        "strength_label": "Veri Yok",
        "top_starting_players": [],
        "top_bench_players": [],
        "unavailable_players": [],
        "important_missing_count": 0,
        "note": "",
        "source_note": ""
      },
      "lineup_quality_diff": 0,
      "lineup_risk_level": "Düşük",
      "robot_comment": "İlk 11 kalite verisi yok. Kadro eksikliği riski: Düşük."
    },
    {
      "match_name": "Nafta VS Koper",
      "league": "Slovenya 1.SNL",
      "start_time": "19:00",
      "home_lineup": {
        "team_name": "Nafta",
        "formation": "-",
        "starting_11_count": 0,
        "substitutes_count": 0,
        "starting_11_strength": 0,
        "bench_strength": 0,
        "strength_label": "Veri Yok",
        "top_starting_players": [],
        "top_bench_players": [],
        "unavailable_players": [],
        "important_missing_count": 0,
        "note": "",
        "source_note": ""
      },
      "away_lineup": {
        "team_name": "Koper",
        "formation": "-",
        "starting_11_count": 0,
        "substitutes_count": 0,
        "starting_11_strength": 0,
        "bench_strength": 0,
        "strength_label": "Veri Yok",
        "top_starting_players": [],
        "top_bench_players": [],
        "unavailable_players": [],
        "important_missing_count": 0,
        "note": "",
        "source_note": ""
      },
      "lineup_quality_diff": 0,
      "lineup_risk_level": "Düşük",
      "robot_comment": "İlk 11 kalite verisi yok. Kadro eksikliği riski: Düşük."
    },
    {
      "match_name": "Flora Tallinn VS Nomme United",
      "league": "Estonya Premium Lig",
      "start_time": "19:00",
      "home_lineup": {
        "team_name": "Flora Tallinn",
        "formation": "-",
        "starting_11_count": 0,
        "substitutes_count": 0,
        "starting_11_strength": 0,
        "bench_strength": 0,
        "strength_label": "Veri Yok",
        "top_starting_players": [],
        "top_bench_players": [],
        "unavailable_players": [],
        "important_missing_count": 0,
        "note": "",
        "source_note": ""
      },
      "away_lineup": {
        "team_name": "Nomme United",
        "formation": "-",
        "starting_11_count": 0,
        "substitutes_count": 0,
        "starting_11_strength": 0,
        "bench_strength": 0,
        "strength_label": "Veri Yok",
        "top_starting_players": [],
        "top_bench_players": [],
        "unavailable_players": [],
        "important_missing_count": 0,
        "note": "",
        "source_note": ""
      },
      "lineup_quality_diff": 0,
      "lineup_risk_level": "Düşük",
      "robot_comment": "İlk 11 kalite verisi yok. Kadro eksikliği riski: Düşük."
    },
    {
      "match_name": "Astoria Walldo VS Darmstadt",
      "league": "Hazırlık Kulüpler",
      "start_time": "19:00",
      "home_lineup": {
        "team_name": "Astoria Walldo",
        "formation": "-",
        "starting_11_count": 0,
        "substitutes_count": 0,
        "starting_11_strength": 0,
        "bench_strength": 0,
        "strength_label": "Veri Yok",
        "top_starting_players": [],
        "top_bench_players": [],
        "unavailable_players": [],
        "important_missing_count": 0,
        "note": "",
        "source_note": ""
      },
      "away_lineup": {
        "team_name": "Darmstadt",
        "formation": "-",
        "starting_11_count": 0,
        "substitutes_count": 0,
        "starting_11_strength": 0,
        "bench_strength": 0,
        "strength_label": "Veri Yok",
        "top_starting_players": [],
        "top_bench_players": [],
        "unavailable_players": [],
        "important_missing_count": 0,
        "note": "",
        "source_note": ""
      },
      "lineup_quality_diff": 0,
      "lineup_risk_level": "Düşük",
      "robot_comment": "İlk 11 kalite verisi yok. Kadro eksikliği riski: Düşük."
    },
    {
      "match_name": "Usti Nad Labem VS Dukla Prag",
      "league": "Hazırlık Kulüpler",
      "start_time": "19:00",
      "home_lineup": {
        "team_name": "Usti Nad Labem",
        "formation": "-",
        "starting_11_count": 0,
        "substitutes_count": 0,
        "starting_11_strength": 0,
        "bench_strength": 0,
        "strength_label": "Veri Yok",
        "top_starting_players": [],
        "top_bench_players": [],
        "unavailable_players": [],
        "important_missing_count": 0,
        "note": "",
        "source_note": ""
      },
      "away_lineup": {
        "team_name": "Dukla Prag",
        "formation": "-",
        "starting_11_count": 0,
        "substitutes_count": 0,
        "starting_11_strength": 0,
        "bench_strength": 0,
        "strength_label": "Veri Yok",
        "top_starting_players": [],
        "top_bench_players": [],
        "unavailable_players": [],
        "important_missing_count": 0,
        "note": "",
        "source_note": ""
      },
      "lineup_quality_diff": 0,
      "lineup_risk_level": "Düşük",
      "robot_comment": "İlk 11 kalite verisi yok. Kadro eksikliği riski: Düşük."
    },
    {
      "match_name": "Elversberg VS Viktoria Köln",
      "league": "Hazırlık Kulüpler",
      "start_time": "19:00",
      "home_lineup": {
        "team_name": "Elversberg",
        "formation": "-",
        "starting_11_count": 0,
        "substitutes_count": 0,
        "starting_11_strength": 0,
        "bench_strength": 0,
        "strength_label": "Veri Yok",
        "top_starting_players": [],
        "top_bench_players": [],
        "unavailable_players": [],
        "important_missing_count": 0,
        "note": "",
        "source_note": ""
      },
      "away_lineup": {
        "team_name": "Viktoria Köln",
        "formation": "-",
        "starting_11_count": 0,
        "substitutes_count": 0,
        "starting_11_strength": 0,
        "bench_strength": 0,
        "strength_label": "Veri Yok",
        "top_starting_players": [],
        "top_bench_players": [],
        "unavailable_players": [],
        "important_missing_count": 0,
        "note": "",
        "source_note": ""
      },
      "lineup_quality_diff": 0,
      "lineup_risk_level": "Düşük",
      "robot_comment": "İlk 11 kalite verisi yok. Kadro eksikliği riski: Düşük."
    },
    {
      "match_name": "Olympiakos VS Fortuna Sittard",
      "league": "Hazırlık Kulüpler",
      "start_time": "19:30",
      "home_lineup": {
        "team_name": "Olympiakos",
        "formation": "-",
        "starting_11_count": 0,
        "substitutes_count": 0,
        "starting_11_strength": 0,
        "bench_strength": 0,
        "strength_label": "Veri Yok",
        "top_starting_players": [],
        "top_bench_players": [],
        "unavailable_players": [],
        "important_missing_count": 0,
        "note": "",
        "source_note": ""
      },
      "away_lineup": {
        "team_name": "Fortuna Sittard",
        "formation": "-",
        "starting_11_count": 0,
        "substitutes_count": 0,
        "starting_11_strength": 0,
        "bench_strength": 0,
        "strength_label": "Veri Yok",
        "top_starting_players": [],
        "top_bench_players": [],
        "unavailable_players": [],
        "important_missing_count": 0,
        "note": "",
        "source_note": ""
      },
      "lineup_quality_diff": 0,
      "lineup_risk_level": "Düşük",
      "robot_comment": "İlk 11 kalite verisi yok. Kadro eksikliği riski: Düşük."
    },
    {
      "match_name": "Eldense VS Millwall",
      "league": "Hazırlık Kulüpler",
      "start_time": "19:30",
      "home_lineup": {
        "team_name": "Eldense",
        "formation": "-",
        "starting_11_count": 0,
        "substitutes_count": 0,
        "starting_11_strength": 0,
        "bench_strength": 0,
        "strength_label": "Veri Yok",
        "top_starting_players": [],
        "top_bench_players": [],
        "unavailable_players": [],
        "important_missing_count": 0,
        "note": "",
        "source_note": ""
      },
      "away_lineup": {
        "team_name": "Millwall",
        "formation": "-",
        "starting_11_count": 0,
        "substitutes_count": 0,
        "starting_11_strength": 0,
        "bench_strength": 0,
        "strength_label": "Veri Yok",
        "top_starting_players": [],
        "top_bench_players": [],
        "unavailable_players": [],
        "important_missing_count": 0,
        "note": "",
        "source_note": ""
      },
      "lineup_quality_diff": 0,
      "lineup_risk_level": "Düşük",
      "robot_comment": "İlk 11 kalite verisi yok. Kadro eksikliği riski: Düşük."
    },
    {
      "match_name": "Wattens VS Hertha Berlin",
      "league": "Hazırlık Kulüpler",
      "start_time": "19:30",
      "home_lineup": {
        "team_name": "Wattens",
        "formation": "-",
        "starting_11_count": 0,
        "substitutes_count": 0,
        "starting_11_strength": 0,
        "bench_strength": 0,
        "strength_label": "Veri Yok",
        "top_starting_players": [],
        "top_bench_players": [],
        "unavailable_players": [],
        "important_missing_count": 0,
        "note": "",
        "source_note": ""
      },
      "away_lineup": {
        "team_name": "Hertha Berlin",
        "formation": "-",
        "starting_11_count": 0,
        "substitutes_count": 0,
        "starting_11_strength": 0,
        "bench_strength": 0,
        "strength_label": "Veri Yok",
        "top_starting_players": [],
        "top_bench_players": [],
        "unavailable_players": [],
        "important_missing_count": 0,
        "note": "",
        "source_note": ""
      },
      "lineup_quality_diff": 0,
      "lineup_risk_level": "Düşük",
      "robot_comment": "İlk 11 kalite verisi yok. Kadro eksikliği riski: Düşük."
    },
    {
      "match_name": "Dac VS Bolton",
      "league": "Hazırlık Kulüpler",
      "start_time": "19:30",
      "home_lineup": {
        "team_name": "Dac",
        "formation": "-",
        "starting_11_count": 0,
        "substitutes_count": 0,
        "starting_11_strength": 0,
        "bench_strength": 0,
        "strength_label": "Veri Yok",
        "top_starting_players": [],
        "top_bench_players": [],
        "unavailable_players": [],
        "important_missing_count": 0,
        "note": "",
        "source_note": ""
      },
      "away_lineup": {
        "team_name": "Bolton",
        "formation": "-",
        "starting_11_count": 0,
        "substitutes_count": 0,
        "starting_11_strength": 0,
        "bench_strength": 0,
        "strength_label": "Veri Yok",
        "top_starting_players": [],
        "top_bench_players": [],
        "unavailable_players": [],
        "important_missing_count": 0,
        "note": "",
        "source_note": ""
      },
      "lineup_quality_diff": 0,
      "lineup_risk_level": "Düşük",
      "robot_comment": "İlk 11 kalite verisi yok. Kadro eksikliği riski: Düşük."
    },
    {
      "match_name": "Göteborg VS Brommapojkarna",
      "league": "İsveç Allsvenskan",
      "start_time": "20:00",
      "home_lineup": {
        "team_name": "Göteborg",
        "formation": "-",
        "starting_11_count": 0,
        "substitutes_count": 0,
        "starting_11_strength": 0,
        "bench_strength": 0,
        "strength_label": "Veri Yok",
        "top_starting_players": [],
        "top_bench_players": [],
        "unavailable_players": [],
        "important_missing_count": 0,
        "note": "",
        "source_note": ""
      },
      "away_lineup": {
        "team_name": "Brommapojkarna",
        "formation": "-",
        "starting_11_count": 0,
        "substitutes_count": 0,
        "starting_11_strength": 0,
        "bench_strength": 0,
        "strength_label": "Veri Yok",
        "top_starting_players": [],
        "top_bench_players": [],
        "unavailable_players": [],
        "important_missing_count": 0,
        "note": "",
        "source_note": ""
      },
      "lineup_quality_diff": 0,
      "lineup_risk_level": "Düşük",
      "robot_comment": "İlk 11 kalite verisi yok. Kadro eksikliği riski: Düşük."
    },
    {
      "match_name": "Mjallby VS Vasteras",
      "league": "İsveç Allsvenskan",
      "start_time": "20:00",
      "home_lineup": {
        "team_name": "Mjallby",
        "formation": "-",
        "starting_11_count": 0,
        "substitutes_count": 0,
        "starting_11_strength": 0,
        "bench_strength": 0,
        "strength_label": "Veri Yok",
        "top_starting_players": [],
        "top_bench_players": [],
        "unavailable_players": [],
        "important_missing_count": 0,
        "note": "",
        "source_note": ""
      },
      "away_lineup": {
        "team_name": "Vasteras",
        "formation": "-",
        "starting_11_count": 0,
        "substitutes_count": 0,
        "starting_11_strength": 0,
        "bench_strength": 0,
        "strength_label": "Veri Yok",
        "top_starting_players": [],
        "top_bench_players": [],
        "unavailable_players": [],
        "important_missing_count": 0,
        "note": "",
        "source_note": ""
      },
      "lineup_quality_diff": 0,
      "lineup_risk_level": "Düşük",
      "robot_comment": "İlk 11 kalite verisi yok. Kadro eksikliği riski: Düşük."
    },
    {
      "match_name": "Club Brugge VS Heerenveen",
      "league": "Hazırlık Kulüpler",
      "start_time": "20:00",
      "home_lineup": {
        "team_name": "Club Brugge",
        "formation": "-",
        "starting_11_count": 0,
        "substitutes_count": 0,
        "starting_11_strength": 0,
        "bench_strength": 0,
        "strength_label": "Veri Yok",
        "top_starting_players": [],
        "top_bench_players": [],
        "unavailable_players": [],
        "important_missing_count": 0,
        "note": "",
        "source_note": ""
      },
      "away_lineup": {
        "team_name": "Heerenveen",
        "formation": "-",
        "starting_11_count": 0,
        "substitutes_count": 0,
        "starting_11_strength": 0,
        "bench_strength": 0,
        "strength_label": "Veri Yok",
        "top_starting_players": [],
        "top_bench_players": [],
        "unavailable_players": [],
        "important_missing_count": 0,
        "note": "",
        "source_note": ""
      },
      "lineup_quality_diff": 0,
      "lineup_risk_level": "Düşük",
      "robot_comment": "İlk 11 kalite verisi yok. Kadro eksikliği riski: Düşük."
    },
    {
      "match_name": "Getafe VS Reading",
      "league": "Hazırlık Kulüpler",
      "start_time": "20:00",
      "home_lineup": {
        "team_name": "Getafe",
        "formation": "-",
        "starting_11_count": 0,
        "substitutes_count": 0,
        "starting_11_strength": 0,
        "bench_strength": 0,
        "strength_label": "Veri Yok",
        "top_starting_players": [],
        "top_bench_players": [],
        "unavailable_players": [],
        "important_missing_count": 0,
        "note": "",
        "source_note": ""
      },
      "away_lineup": {
        "team_name": "Reading",
        "formation": "-",
        "starting_11_count": 0,
        "substitutes_count": 0,
        "starting_11_strength": 0,
        "bench_strength": 0,
        "strength_label": "Veri Yok",
        "top_starting_players": [],
        "top_bench_players": [],
        "unavailable_players": [],
        "important_missing_count": 0,
        "note": "",
        "source_note": ""
      },
      "lineup_quality_diff": 0,
      "lineup_risk_level": "Düşük",
      "robot_comment": "İlk 11 kalite verisi yok. Kadro eksikliği riski: Düşük."
    },
    {
      "match_name": "Winterthur VS Union Berlin",
      "league": "Hazırlık Kulüpler",
      "start_time": "20:00",
      "home_lineup": {
        "team_name": "Winterthur",
        "formation": "-",
        "starting_11_count": 0,
        "substitutes_count": 0,
        "starting_11_strength": 0,
        "bench_strength": 0,
        "strength_label": "Veri Yok",
        "top_starting_players": [],
        "top_bench_players": [],
        "unavailable_players": [],
        "important_missing_count": 0,
        "note": "",
        "source_note": ""
      },
      "away_lineup": {
        "team_name": "Union Berlin",
        "formation": "-",
        "starting_11_count": 0,
        "substitutes_count": 0,
        "starting_11_strength": 0,
        "bench_strength": 0,
        "strength_label": "Veri Yok",
        "top_starting_players": [],
        "top_bench_players": [],
        "unavailable_players": [],
        "important_missing_count": 0,
        "note": "",
        "source_note": ""
      },
      "lineup_quality_diff": 0,
      "lineup_risk_level": "Düşük",
      "robot_comment": "İlk 11 kalite verisi yok. Kadro eksikliği riski: Düşük."
    },
    {
      "match_name": "Bodo Glimt VS Fredrikstad",
      "league": "Norveç Eliteserien",
      "start_time": "20:15",
      "home_lineup": {
        "team_name": "Bodo Glimt",
        "formation": "-",
        "starting_11_count": 0,
        "substitutes_count": 0,
        "starting_11_strength": 0,
        "bench_strength": 0,
        "strength_label": "Veri Yok",
        "top_starting_players": [],
        "top_bench_players": [],
        "unavailable_players": [],
        "important_missing_count": 0,
        "note": "",
        "source_note": ""
      },
      "away_lineup": {
        "team_name": "Fredrikstad",
        "formation": "-",
        "starting_11_count": 0,
        "substitutes_count": 0,
        "starting_11_strength": 0,
        "bench_strength": 0,
        "strength_label": "Veri Yok",
        "top_starting_players": [],
        "top_bench_players": [],
        "unavailable_players": [],
        "important_missing_count": 0,
        "note": "",
        "source_note": ""
      },
      "lineup_quality_diff": 0,
      "lineup_risk_level": "Düşük",
      "robot_comment": "İlk 11 kalite verisi yok. Kadro eksikliği riski: Düşük."
    },
    {
      "match_name": "West Bromwich VS Bromley",
      "league": "Hazırlık Kulüpler",
      "start_time": "21:00",
      "home_lineup": {
        "team_name": "West Bromwich",
        "formation": "-",
        "starting_11_count": 0,
        "substitutes_count": 0,
        "starting_11_strength": 0,
        "bench_strength": 0,
        "strength_label": "Veri Yok",
        "top_starting_players": [],
        "top_bench_players": [],
        "unavailable_players": [],
        "important_missing_count": 0,
        "note": "",
        "source_note": ""
      },
      "away_lineup": {
        "team_name": "Bromley",
        "formation": "-",
        "starting_11_count": 0,
        "substitutes_count": 0,
        "starting_11_strength": 0,
        "bench_strength": 0,
        "strength_label": "Veri Yok",
        "top_starting_players": [],
        "top_bench_players": [],
        "unavailable_players": [],
        "important_missing_count": 0,
        "note": "",
        "source_note": ""
      },
      "lineup_quality_diff": 0,
      "lineup_risk_level": "Düşük",
      "robot_comment": "İlk 11 kalite verisi yok. Kadro eksikliği riski: Düşük."
    },
    {
      "match_name": "Motherwell VS Genk",
      "league": "Hazırlık Kulüpler",
      "start_time": "21:00",
      "home_lineup": {
        "team_name": "Motherwell",
        "formation": "-",
        "starting_11_count": 0,
        "substitutes_count": 0,
        "starting_11_strength": 0,
        "bench_strength": 0,
        "strength_label": "Veri Yok",
        "top_starting_players": [],
        "top_bench_players": [],
        "unavailable_players": [],
        "important_missing_count": 0,
        "note": "",
        "source_note": ""
      },
      "away_lineup": {
        "team_name": "Genk",
        "formation": "-",
        "starting_11_count": 0,
        "substitutes_count": 0,
        "starting_11_strength": 0,
        "bench_strength": 0,
        "strength_label": "Veri Yok",
        "top_starting_players": [],
        "top_bench_players": [],
        "unavailable_players": [],
        "important_missing_count": 0,
        "note": "",
        "source_note": ""
      },
      "lineup_quality_diff": 0,
      "lineup_risk_level": "Düşük",
      "robot_comment": "İlk 11 kalite verisi yok. Kadro eksikliği riski: Düşük."
    },
    {
      "match_name": "Austria Vienna VS Paksi",
      "league": "Hazırlık Kulüpler",
      "start_time": "21:00",
      "home_lineup": {
        "team_name": "Austria Vienna",
        "formation": "-",
        "starting_11_count": 0,
        "substitutes_count": 0,
        "starting_11_strength": 0,
        "bench_strength": 0,
        "strength_label": "Veri Yok",
        "top_starting_players": [],
        "top_bench_players": [],
        "unavailable_players": [],
        "important_missing_count": 0,
        "note": "",
        "source_note": ""
      },
      "away_lineup": {
        "team_name": "Paksi",
        "formation": "-",
        "starting_11_count": 0,
        "substitutes_count": 0,
        "starting_11_strength": 0,
        "bench_strength": 0,
        "strength_label": "Veri Yok",
        "top_starting_players": [],
        "top_bench_players": [],
        "unavailable_players": [],
        "important_missing_count": 0,
        "note": "",
        "source_note": ""
      },
      "lineup_quality_diff": 0,
      "lineup_risk_level": "Düşük",
      "robot_comment": "İlk 11 kalite verisi yok. Kadro eksikliği riski: Düşük."
    },
    {
      "match_name": "Alfreton VS Derby County",
      "league": "Hazırlık Kulüpler",
      "start_time": "21:00",
      "home_lineup": {
        "team_name": "Alfreton",
        "formation": "-",
        "starting_11_count": 0,
        "substitutes_count": 0,
        "starting_11_strength": 0,
        "bench_strength": 0,
        "strength_label": "Veri Yok",
        "top_starting_players": [],
        "top_bench_players": [],
        "unavailable_players": [],
        "important_missing_count": 0,
        "note": "",
        "source_note": ""
      },
      "away_lineup": {
        "team_name": "Derby County",
        "formation": "-",
        "starting_11_count": 0,
        "substitutes_count": 0,
        "starting_11_strength": 0,
        "bench_strength": 0,
        "strength_label": "Veri Yok",
        "top_starting_players": [],
        "top_bench_players": [],
        "unavailable_players": [],
        "important_missing_count": 0,
        "note": "",
        "source_note": ""
      },
      "lineup_quality_diff": 0,
      "lineup_risk_level": "Düşük",
      "robot_comment": "İlk 11 kalite verisi yok. Kadro eksikliği riski: Düşük."
    },
    {
      "match_name": "Yamoussoukro VS Marsilya",
      "league": "Hazırlık Kulüpler",
      "start_time": "21:00",
      "home_lineup": {
        "team_name": "Yamoussoukro",
        "formation": "-",
        "starting_11_count": 0,
        "substitutes_count": 0,
        "starting_11_strength": 0,
        "bench_strength": 0,
        "strength_label": "Veri Yok",
        "top_starting_players": [],
        "top_bench_players": [],
        "unavailable_players": [],
        "important_missing_count": 0,
        "note": "",
        "source_note": ""
      },
      "away_lineup": {
        "team_name": "Marsilya",
        "formation": "-",
        "starting_11_count": 0,
        "substitutes_count": 0,
        "starting_11_strength": 0,
        "bench_strength": 0,
        "strength_label": "Veri Yok",
        "top_starting_players": [],
        "top_bench_players": [],
        "unavailable_players": [],
        "important_missing_count": 0,
        "note": "",
        "source_note": ""
      },
      "lineup_quality_diff": 0,
      "lineup_risk_level": "Düşük",
      "robot_comment": "İlk 11 kalite verisi yok. Kadro eksikliği riski: Düşük."
    },
    {
      "match_name": "Kizilyildiz VS Macva",
      "league": "Sırbistan Süper Lig",
      "start_time": "21:00",
      "home_lineup": {
        "team_name": "Kizilyildiz",
        "formation": "-",
        "starting_11_count": 0,
        "substitutes_count": 0,
        "starting_11_strength": 0,
        "bench_strength": 0,
        "strength_label": "Veri Yok",
        "top_starting_players": [],
        "top_bench_players": [],
        "unavailable_players": [],
        "important_missing_count": 0,
        "note": "",
        "source_note": ""
      },
      "away_lineup": {
        "team_name": "Macva",
        "formation": "-",
        "starting_11_count": 0,
        "substitutes_count": 0,
        "starting_11_strength": 0,
        "bench_strength": 0,
        "strength_label": "Veri Yok",
        "top_starting_players": [],
        "top_bench_players": [],
        "unavailable_players": [],
        "important_missing_count": 0,
        "note": "",
        "source_note": ""
      },
      "lineup_quality_diff": 0,
      "lineup_risk_level": "Düşük",
      "robot_comment": "İlk 11 kalite verisi yok. Kadro eksikliği riski: Düşük."
    },
    {
      "match_name": "Zeleznicar Pan VS Radnicki Nis",
      "league": "Sırbistan Süper Lig",
      "start_time": "21:00",
      "home_lineup": {
        "team_name": "Zeleznicar Pan",
        "formation": "-",
        "starting_11_count": 0,
        "substitutes_count": 0,
        "starting_11_strength": 0,
        "bench_strength": 0,
        "strength_label": "Veri Yok",
        "top_starting_players": [],
        "top_bench_players": [],
        "unavailable_players": [],
        "important_missing_count": 0,
        "note": "",
        "source_note": ""
      },
      "away_lineup": {
        "team_name": "Radnicki Nis",
        "formation": "-",
        "starting_11_count": 0,
        "substitutes_count": 0,
        "starting_11_strength": 0,
        "bench_strength": 0,
        "strength_label": "Veri Yok",
        "top_starting_players": [],
        "top_bench_players": [],
        "unavailable_players": [],
        "important_missing_count": 0,
        "note": "",
        "source_note": ""
      },
      "lineup_quality_diff": 0,
      "lineup_risk_level": "Düşük",
      "robot_comment": "İlk 11 kalite verisi yok. Kadro eksikliği riski: Düşük."
    },
    {
      "match_name": "Fc Cajamarca VS Juan Pablo Ii C",
      "league": "Peru Premier Lig Clausura",
      "start_time": "21:00",
      "home_lineup": {
        "team_name": "Fc Cajamarca",
        "formation": "-",
        "starting_11_count": 0,
        "substitutes_count": 0,
        "starting_11_strength": 0,
        "bench_strength": 0,
        "strength_label": "Veri Yok",
        "top_starting_players": [],
        "top_bench_players": [],
        "unavailable_players": [],
        "important_missing_count": 0,
        "note": "",
        "source_note": ""
      },
      "away_lineup": {
        "team_name": "Juan Pablo Ii C",
        "formation": "-",
        "starting_11_count": 0,
        "substitutes_count": 0,
        "starting_11_strength": 0,
        "bench_strength": 0,
        "strength_label": "Veri Yok",
        "top_starting_players": [],
        "top_bench_players": [],
        "unavailable_players": [],
        "important_missing_count": 0,
        "note": "",
        "source_note": ""
      },
      "lineup_quality_diff": 0,
      "lineup_risk_level": "Düşük",
      "robot_comment": "İlk 11 kalite verisi yok. Kadro eksikliği riski: Düşük."
    },
    {
      "match_name": "Almirante VS Caseros",
      "league": "Arjantin Ulusal Primera Lig",
      "start_time": "21:00",
      "home_lineup": {
        "team_name": "Almirante",
        "formation": "-",
        "starting_11_count": 0,
        "substitutes_count": 0,
        "starting_11_strength": 0,
        "bench_strength": 0,
        "strength_label": "Veri Yok",
        "top_starting_players": [],
        "top_bench_players": [],
        "unavailable_players": [],
        "important_missing_count": 0,
        "note": "",
        "source_note": ""
      },
      "away_lineup": {
        "team_name": "Caseros",
        "formation": "-",
        "starting_11_count": 0,
        "substitutes_count": 0,
        "starting_11_strength": 0,
        "bench_strength": 0,
        "strength_label": "Veri Yok",
        "top_starting_players": [],
        "top_bench_players": [],
        "unavailable_players": [],
        "important_missing_count": 0,
        "note": "",
        "source_note": ""
      },
      "lineup_quality_diff": 0,
      "lineup_risk_level": "Düşük",
      "robot_comment": "İlk 11 kalite verisi yok. Kadro eksikliği riski: Düşük."
    },
    {
      "match_name": "Maipu VS San Martin Tucu",
      "league": "Arjantin Ulusal Primera Lig",
      "start_time": "21:00",
      "home_lineup": {
        "team_name": "Maipu",
        "formation": "-",
        "starting_11_count": 0,
        "substitutes_count": 0,
        "starting_11_strength": 0,
        "bench_strength": 0,
        "strength_label": "Veri Yok",
        "top_starting_players": [],
        "top_bench_players": [],
        "unavailable_players": [],
        "important_missing_count": 0,
        "note": "",
        "source_note": ""
      },
      "away_lineup": {
        "team_name": "San Martin Tucu",
        "formation": "-",
        "starting_11_count": 0,
        "substitutes_count": 0,
        "starting_11_strength": 0,
        "bench_strength": 0,
        "strength_label": "Veri Yok",
        "top_starting_players": [],
        "top_bench_players": [],
        "unavailable_players": [],
        "important_missing_count": 0,
        "note": "",
        "source_note": ""
      },
      "lineup_quality_diff": 0,
      "lineup_risk_level": "Düşük",
      "robot_comment": "İlk 11 kalite verisi yok. Kadro eksikliği riski: Düşük."
    },
    {
      "match_name": "Albion VS Juventud Dl Pie",
      "league": "Uruguay Premier Lig Intermediate Turu Grup 2",
      "start_time": "21:00",
      "home_lineup": {
        "team_name": "Albion",
        "formation": "-",
        "starting_11_count": 0,
        "substitutes_count": 0,
        "starting_11_strength": 0,
        "bench_strength": 0,
        "strength_label": "Veri Yok",
        "top_starting_players": [],
        "top_bench_players": [],
        "unavailable_players": [],
        "important_missing_count": 0,
        "note": "",
        "source_note": ""
      },
      "away_lineup": {
        "team_name": "Juventud Dl Pie",
        "formation": "-",
        "starting_11_count": 0,
        "substitutes_count": 0,
        "starting_11_strength": 0,
        "bench_strength": 0,
        "strength_label": "Veri Yok",
        "top_starting_players": [],
        "top_bench_players": [],
        "unavailable_players": [],
        "important_missing_count": 0,
        "note": "",
        "source_note": ""
      },
      "lineup_quality_diff": 0,
      "lineup_risk_level": "Düşük",
      "robot_comment": "İlk 11 kalite verisi yok. Kadro eksikliği riski: Düşük."
    },
    {
      "match_name": "St Gallen VS Norwich",
      "league": "Hazırlık Kulüpler",
      "start_time": "21:00",
      "home_lineup": {
        "team_name": "St Gallen",
        "formation": "-",
        "starting_11_count": 0,
        "substitutes_count": 0,
        "starting_11_strength": 0,
        "bench_strength": 0,
        "strength_label": "Veri Yok",
        "top_starting_players": [],
        "top_bench_players": [],
        "unavailable_players": [],
        "important_missing_count": 0,
        "note": "",
        "source_note": ""
      },
      "away_lineup": {
        "team_name": "Norwich",
        "formation": "-",
        "starting_11_count": 0,
        "substitutes_count": 0,
        "starting_11_strength": 0,
        "bench_strength": 0,
        "strength_label": "Veri Yok",
        "top_starting_players": [],
        "top_bench_players": [],
        "unavailable_players": [],
        "important_missing_count": 0,
        "note": "",
        "source_note": ""
      },
      "lineup_quality_diff": 0,
      "lineup_risk_level": "Düşük",
      "robot_comment": "İlk 11 kalite verisi yok. Kadro eksikliği riski: Düşük."
    },
    {
      "match_name": "Lugano VS Vaduz",
      "league": "Hazırlık Kulüpler",
      "start_time": "21:15",
      "home_lineup": {
        "team_name": "Lugano",
        "formation": "-",
        "starting_11_count": 0,
        "substitutes_count": 0,
        "starting_11_strength": 0,
        "bench_strength": 0,
        "strength_label": "Veri Yok",
        "top_starting_players": [],
        "top_bench_players": [],
        "unavailable_players": [],
        "important_missing_count": 0,
        "note": "",
        "source_note": ""
      },
      "away_lineup": {
        "team_name": "Vaduz",
        "formation": "-",
        "starting_11_count": 0,
        "substitutes_count": 0,
        "starting_11_strength": 0,
        "bench_strength": 0,
        "strength_label": "Veri Yok",
        "top_starting_players": [],
        "top_bench_players": [],
        "unavailable_players": [],
        "important_missing_count": 0,
        "note": "",
        "source_note": ""
      },
      "lineup_quality_diff": 0,
      "lineup_risk_level": "Düşük",
      "robot_comment": "İlk 11 kalite verisi yok. Kadro eksikliği riski: Düşük."
    },
    {
      "match_name": "Levski Sofya VS Dunav 2010",
      "league": "Bulgaristan 1.Lig",
      "start_time": "21:15",
      "home_lineup": {
        "team_name": "Levski Sofya",
        "formation": "-",
        "starting_11_count": 0,
        "substitutes_count": 0,
        "starting_11_strength": 0,
        "bench_strength": 0,
        "strength_label": "Veri Yok",
        "top_starting_players": [],
        "top_bench_players": [],
        "unavailable_players": [],
        "important_missing_count": 0,
        "note": "",
        "source_note": ""
      },
      "away_lineup": {
        "team_name": "Dunav 2010",
        "formation": "-",
        "starting_11_count": 0,
        "substitutes_count": 0,
        "starting_11_strength": 0,
        "bench_strength": 0,
        "strength_label": "Veri Yok",
        "top_starting_players": [],
        "top_bench_players": [],
        "unavailable_players": [],
        "important_missing_count": 0,
        "note": "",
        "source_note": ""
      },
      "lineup_quality_diff": 0,
      "lineup_risk_level": "Düşük",
      "robot_comment": "İlk 11 kalite verisi yok. Kadro eksikliği riski: Düşük."
    },
    {
      "match_name": "Celje VS Mura",
      "league": "Slovenya 1.SNL",
      "start_time": "21:15",
      "home_lineup": {
        "team_name": "Celje",
        "formation": "-",
        "starting_11_count": 0,
        "substitutes_count": 0,
        "starting_11_strength": 0,
        "bench_strength": 0,
        "strength_label": "Veri Yok",
        "top_starting_players": [],
        "top_bench_players": [],
        "unavailable_players": [],
        "important_missing_count": 0,
        "note": "",
        "source_note": ""
      },
      "away_lineup": {
        "team_name": "Mura",
        "formation": "-",
        "starting_11_count": 0,
        "substitutes_count": 0,
        "starting_11_strength": 0,
        "bench_strength": 0,
        "strength_label": "Veri Yok",
        "top_starting_players": [],
        "top_bench_players": [],
        "unavailable_players": [],
        "important_missing_count": 0,
        "note": "",
        "source_note": ""
      },
      "lineup_quality_diff": 0,
      "lineup_risk_level": "Düşük",
      "robot_comment": "İlk 11 kalite verisi yok. Kadro eksikliği riski: Düşük."
    },
    {
      "match_name": "Fc Steaua VS Argesul Pitesti",
      "league": "Romanya 1.Lig",
      "start_time": "21:30",
      "home_lineup": {
        "team_name": "Fc Steaua",
        "formation": "-",
        "starting_11_count": 0,
        "substitutes_count": 0,
        "starting_11_strength": 0,
        "bench_strength": 0,
        "strength_label": "Veri Yok",
        "top_starting_players": [],
        "top_bench_players": [],
        "unavailable_players": [],
        "important_missing_count": 0,
        "note": "",
        "source_note": ""
      },
      "away_lineup": {
        "team_name": "Argesul Pitesti",
        "formation": "-",
        "starting_11_count": 0,
        "substitutes_count": 0,
        "starting_11_strength": 0,
        "bench_strength": 0,
        "strength_label": "Veri Yok",
        "top_starting_players": [],
        "top_bench_players": [],
        "unavailable_players": [],
        "important_missing_count": 0,
        "note": "",
        "source_note": ""
      },
      "lineup_quality_diff": 0,
      "lineup_risk_level": "Düşük",
      "robot_comment": "İlk 11 kalite verisi yok. Kadro eksikliği riski: Düşük."
    },
    {
      "match_name": "Hearts VS Vallecano",
      "league": "Hazırlık Kulüpler",
      "start_time": "21:45",
      "home_lineup": {
        "team_name": "Hearts",
        "formation": "-",
        "starting_11_count": 0,
        "substitutes_count": 0,
        "starting_11_strength": 0,
        "bench_strength": 0,
        "strength_label": "Veri Yok",
        "top_starting_players": [],
        "top_bench_players": [],
        "unavailable_players": [],
        "important_missing_count": 0,
        "note": "",
        "source_note": ""
      },
      "away_lineup": {
        "team_name": "Vallecano",
        "formation": "-",
        "starting_11_count": 0,
        "substitutes_count": 0,
        "starting_11_strength": 0,
        "bench_strength": 0,
        "strength_label": "Veri Yok",
        "top_starting_players": [],
        "top_bench_players": [],
        "unavailable_players": [],
        "important_missing_count": 0,
        "note": "",
        "source_note": ""
      },
      "lineup_quality_diff": 0,
      "lineup_risk_level": "Düşük",
      "robot_comment": "İlk 11 kalite verisi yok. Kadro eksikliği riski: Düşük."
    },
    {
      "match_name": "Benfica VS Villarreal",
      "league": "Hazırlık Kulüpler",
      "start_time": "21:45",
      "home_lineup": {
        "team_name": "Benfica",
        "formation": "-",
        "starting_11_count": 0,
        "substitutes_count": 0,
        "starting_11_strength": 0,
        "bench_strength": 0,
        "strength_label": "Veri Yok",
        "top_starting_players": [],
        "top_bench_players": [],
        "unavailable_players": [],
        "important_missing_count": 0,
        "note": "",
        "source_note": ""
      },
      "away_lineup": {
        "team_name": "Villarreal",
        "formation": "-",
        "starting_11_count": 0,
        "substitutes_count": 0,
        "starting_11_strength": 0,
        "bench_strength": 0,
        "strength_label": "Veri Yok",
        "top_starting_players": [],
        "top_bench_players": [],
        "unavailable_players": [],
        "important_missing_count": 0,
        "note": "",
        "source_note": ""
      },
      "lineup_quality_diff": 0,
      "lineup_risk_level": "Düşük",
      "robot_comment": "İlk 11 kalite verisi yok. Kadro eksikliği riski: Düşük."
    },
    {
      "match_name": "Ca Mitre VS R Cordoba",
      "league": "Arjantin Ulusal Primera Lig",
      "start_time": "22:00",
      "home_lineup": {
        "team_name": "Ca Mitre",
        "formation": "-",
        "starting_11_count": 0,
        "substitutes_count": 0,
        "starting_11_strength": 0,
        "bench_strength": 0,
        "strength_label": "Veri Yok",
        "top_starting_players": [],
        "top_bench_players": [],
        "unavailable_players": [],
        "important_missing_count": 0,
        "note": "",
        "source_note": ""
      },
      "away_lineup": {
        "team_name": "R Cordoba",
        "formation": "-",
        "starting_11_count": 0,
        "substitutes_count": 0,
        "starting_11_strength": 0,
        "bench_strength": 0,
        "strength_label": "Veri Yok",
        "top_starting_players": [],
        "top_bench_players": [],
        "unavailable_players": [],
        "important_missing_count": 0,
        "note": "",
        "source_note": ""
      },
      "lineup_quality_diff": 0,
      "lineup_risk_level": "Düşük",
      "robot_comment": "İlk 11 kalite verisi yok. Kadro eksikliği riski: Düşük."
    },
    {
      "match_name": "Yamoussoukro VS Marsilya",
      "league": "Hazırlık Kulüpler",
      "start_time": "22:00",
      "home_lineup": {
        "team_name": "Yamoussoukro",
        "formation": "-",
        "starting_11_count": 0,
        "substitutes_count": 0,
        "starting_11_strength": 0,
        "bench_strength": 0,
        "strength_label": "Veri Yok",
        "top_starting_players": [],
        "top_bench_players": [],
        "unavailable_players": [],
        "important_missing_count": 0,
        "note": "",
        "source_note": ""
      },
      "away_lineup": {
        "team_name": "Marsilya",
        "formation": "-",
        "starting_11_count": 0,
        "substitutes_count": 0,
        "starting_11_strength": 0,
        "bench_strength": 0,
        "strength_label": "Veri Yok",
        "top_starting_players": [],
        "top_bench_players": [],
        "unavailable_players": [],
        "important_missing_count": 0,
        "note": "",
        "source_note": ""
      },
      "lineup_quality_diff": 0,
      "lineup_risk_level": "Düşük",
      "robot_comment": "İlk 11 kalite verisi yok. Kadro eksikliği riski: Düşük."
    },
    {
      "match_name": "El Massira VS Uts Rabat",
      "league": "Fas Botola Pro Yükselme/Küme Düşme Play Off 1/2",
      "start_time": "22:00",
      "home_lineup": {
        "team_name": "El Massira",
        "formation": "-",
        "starting_11_count": 0,
        "substitutes_count": 0,
        "starting_11_strength": 0,
        "bench_strength": 0,
        "strength_label": "Veri Yok",
        "top_starting_players": [],
        "top_bench_players": [],
        "unavailable_players": [],
        "important_missing_count": 0,
        "note": "",
        "source_note": ""
      },
      "away_lineup": {
        "team_name": "Uts Rabat",
        "formation": "-",
        "starting_11_count": 0,
        "substitutes_count": 0,
        "starting_11_strength": 0,
        "bench_strength": 0,
        "strength_label": "Veri Yok",
        "top_starting_players": [],
        "top_bench_players": [],
        "unavailable_players": [],
        "important_missing_count": 0,
        "note": "",
        "source_note": ""
      },
      "lineup_quality_diff": 0,
      "lineup_risk_level": "Düşük",
      "robot_comment": "İlk 11 kalite verisi yok. Kadro eksikliği riski: Düşük."
    },
    {
      "match_name": "Fylkir VS Njardvik",
      "league": "İzlanda 1.Lig",
      "start_time": "22:15",
      "home_lineup": {
        "team_name": "Fylkir",
        "formation": "-",
        "starting_11_count": 0,
        "substitutes_count": 0,
        "starting_11_strength": 0,
        "bench_strength": 0,
        "strength_label": "Veri Yok",
        "top_starting_players": [],
        "top_bench_players": [],
        "unavailable_players": [],
        "important_missing_count": 0,
        "note": "",
        "source_note": ""
      },
      "away_lineup": {
        "team_name": "Njardvik",
        "formation": "-",
        "starting_11_count": 0,
        "substitutes_count": 0,
        "starting_11_strength": 0,
        "bench_strength": 0,
        "strength_label": "Veri Yok",
        "top_starting_players": [],
        "top_bench_players": [],
        "unavailable_players": [],
        "important_missing_count": 0,
        "note": "",
        "source_note": ""
      },
      "lineup_quality_diff": 0,
      "lineup_risk_level": "Düşük",
      "robot_comment": "İlk 11 kalite verisi yok. Kadro eksikliği riski: Düşük."
    },
    {
      "match_name": "Haukar VS Throttur Vogar",
      "league": "İzlanda 2.Lig",
      "start_time": "22:15",
      "home_lineup": {
        "team_name": "Haukar",
        "formation": "-",
        "starting_11_count": 0,
        "substitutes_count": 0,
        "starting_11_strength": 0,
        "bench_strength": 0,
        "strength_label": "Veri Yok",
        "top_starting_players": [],
        "top_bench_players": [],
        "unavailable_players": [],
        "important_missing_count": 0,
        "note": "",
        "source_note": ""
      },
      "away_lineup": {
        "team_name": "Throttur Vogar",
        "formation": "-",
        "starting_11_count": 0,
        "substitutes_count": 0,
        "starting_11_strength": 0,
        "bench_strength": 0,
        "strength_label": "Veri Yok",
        "top_starting_players": [],
        "top_bench_players": [],
        "unavailable_players": [],
        "important_missing_count": 0,
        "note": "",
        "source_note": ""
      },
      "lineup_quality_diff": 0,
      "lineup_risk_level": "Düşük",
      "robot_comment": "İlk 11 kalite verisi yok. Kadro eksikliği riski: Düşük."
    },
    {
      "match_name": "Kfg Gardabar VS Kari",
      "league": "İzlanda 2.Lig",
      "start_time": "22:15",
      "home_lineup": {
        "team_name": "Kfg Gardabar",
        "formation": "-",
        "starting_11_count": 0,
        "substitutes_count": 0,
        "starting_11_strength": 0,
        "bench_strength": 0,
        "strength_label": "Veri Yok",
        "top_starting_players": [],
        "top_bench_players": [],
        "unavailable_players": [],
        "important_missing_count": 0,
        "note": "",
        "source_note": ""
      },
      "away_lineup": {
        "team_name": "Kari",
        "formation": "-",
        "starting_11_count": 0,
        "substitutes_count": 0,
        "starting_11_strength": 0,
        "bench_strength": 0,
        "strength_label": "Veri Yok",
        "top_starting_players": [],
        "top_bench_players": [],
        "unavailable_players": [],
        "important_missing_count": 0,
        "note": "",
        "source_note": ""
      },
      "lineup_quality_diff": 0,
      "lineup_risk_level": "Düşük",
      "robot_comment": "İlk 11 kalite verisi yok. Kadro eksikliği riski: Düşük."
    },
    {
      "match_name": "Steel City VS Northern Indian",
      "league": "ABD USL Lig 2 Konferans Çeyrek Final",
      "start_time": "23:00",
      "home_lineup": {
        "team_name": "Steel City",
        "formation": "-",
        "starting_11_count": 0,
        "substitutes_count": 0,
        "starting_11_strength": 0,
        "bench_strength": 0,
        "strength_label": "Veri Yok",
        "top_starting_players": [],
        "top_bench_players": [],
        "unavailable_players": [],
        "important_missing_count": 0,
        "note": "",
        "source_note": ""
      },
      "away_lineup": {
        "team_name": "Northern Indian",
        "formation": "-",
        "starting_11_count": 0,
        "substitutes_count": 0,
        "starting_11_strength": 0,
        "bench_strength": 0,
        "strength_label": "Veri Yok",
        "top_starting_players": [],
        "top_bench_players": [],
        "unavailable_players": [],
        "important_missing_count": 0,
        "note": "",
        "source_note": ""
      },
      "lineup_quality_diff": 0,
      "lineup_risk_level": "Düşük",
      "robot_comment": "İlk 11 kalite verisi yok. Kadro eksikliği riski: Düşük."
    },
    {
      "match_name": "Hviti VS Vikingur Ol.",
      "league": "İzlanda 2.Lig",
      "start_time": "23:00",
      "home_lineup": {
        "team_name": "Hviti",
        "formation": "-",
        "starting_11_count": 0,
        "substitutes_count": 0,
        "starting_11_strength": 0,
        "bench_strength": 0,
        "strength_label": "Veri Yok",
        "top_starting_players": [],
        "top_bench_players": [],
        "unavailable_players": [],
        "important_missing_count": 0,
        "note": "",
        "source_note": ""
      },
      "away_lineup": {
        "team_name": "Vikingur Ol.",
        "formation": "-",
        "starting_11_count": 0,
        "substitutes_count": 0,
        "starting_11_strength": 0,
        "bench_strength": 0,
        "strength_label": "Veri Yok",
        "top_starting_players": [],
        "top_bench_players": [],
        "unavailable_players": [],
        "important_missing_count": 0,
        "note": "",
        "source_note": ""
      },
      "lineup_quality_diff": 0,
      "lineup_risk_level": "Düşük",
      "robot_comment": "İlk 11 kalite verisi yok. Kadro eksikliği riski: Düşük."
    },
    {
      "match_name": "Ocean City VS Fc Motown Ii",
      "league": "ABD USL Lig 2 Konferans Çeyrek Final",
      "start_time": "23:00",
      "home_lineup": {
        "team_name": "Ocean City",
        "formation": "-",
        "starting_11_count": 0,
        "substitutes_count": 0,
        "starting_11_strength": 0,
        "bench_strength": 0,
        "strength_label": "Veri Yok",
        "top_starting_players": [],
        "top_bench_players": [],
        "unavailable_players": [],
        "important_missing_count": 0,
        "note": "",
        "source_note": ""
      },
      "away_lineup": {
        "team_name": "Fc Motown Ii",
        "formation": "-",
        "starting_11_count": 0,
        "substitutes_count": 0,
        "starting_11_strength": 0,
        "bench_strength": 0,
        "strength_label": "Veri Yok",
        "top_starting_players": [],
        "top_bench_players": [],
        "unavailable_players": [],
        "important_missing_count": 0,
        "note": "",
        "source_note": ""
      },
      "lineup_quality_diff": 0,
      "lineup_risk_level": "Düşük",
      "robot_comment": "İlk 11 kalite verisi yok. Kadro eksikliği riski: Düşük."
    },
    {
      "match_name": "Sporting Crist VS Deportivo Garci",
      "league": "Peru Premier Lig Clausura",
      "start_time": "23:15",
      "home_lineup": {
        "team_name": "Sporting Crist",
        "formation": "-",
        "starting_11_count": 0,
        "substitutes_count": 0,
        "starting_11_strength": 0,
        "bench_strength": 0,
        "strength_label": "Veri Yok",
        "top_starting_players": [],
        "top_bench_players": [],
        "unavailable_players": [],
        "important_missing_count": 0,
        "note": "",
        "source_note": ""
      },
      "away_lineup": {
        "team_name": "Deportivo Garci",
        "formation": "-",
        "starting_11_count": 0,
        "substitutes_count": 0,
        "starting_11_strength": 0,
        "bench_strength": 0,
        "strength_label": "Veri Yok",
        "top_starting_players": [],
        "top_bench_players": [],
        "unavailable_players": [],
        "important_missing_count": 0,
        "note": "",
        "source_note": ""
      },
      "lineup_quality_diff": 0,
      "lineup_risk_level": "Düşük",
      "robot_comment": "İlk 11 kalite verisi yok. Kadro eksikliği riski: Düşük."
    }
  ]
}
